quickverifyimg/__init__.py
quickverifyimg/quick_verify.py
quickverifyimg/quick_verify_simple.py
quickverifyimg/quick_verify_video.py
quickverifyimg/log/__init__.py
quickverifyimg/log/logger.py
quickverifyimg/utils/__init__.py
quickverifyimg/utils/aircv_utils.py
quickverifyimg/utils/analyze.py
quickverifyimg/utils/crop_utils.py
quickverifyimg/utils/cv2_utils.py
quickverifyimg/utils/hash_utils.py
quickverifyimg/utils/image_utils.py
quickverifyimg/utils/psnr.py
quickverifyimg/utils/pysift.py
quickverifyimg/utils/sift_utils.py
quickverifyimg/utils/thread_utils.py
tests/__init__.py
tests/analyze_memory.py
tests/verify_img_test.py
tests/verify_test.py
tests/verify_video_test.py
quickverifyimg-1.0.23.dist-info/LICENSE
quickverifyimg-1.0.23.dist-info/METADATA
quickverifyimg-1.0.23.dist-info/WHEEL
quickverifyimg-1.0.23.dist-info/top_level.txt
quickverifyimg-1.0.23.dist-info/RECORD
